woss/contracts/__init__.py
woss.contracts-0.0.3.dist-info/LICENSE
woss.contracts-0.0.3.dist-info/WHEEL
woss.contracts-0.0.3.dist-info/METADATA
woss.contracts-0.0.3.dist-info/RECORD
